pyeumonia/__init__.py
pyeumonia/covid19.py
pyeumonia-0.6.5b0.dist-info/LICENSE
pyeumonia-0.6.5b0.dist-info/LICENSE-zh_CN
pyeumonia-0.6.5b0.dist-info/METADATA
pyeumonia-0.6.5b0.dist-info/WHEEL
pyeumonia-0.6.5b0.dist-info/top_level.txt
pyeumonia-0.6.5b0.dist-info/RECORD
