Metadata-Version: 2.1
Name: pyeumonia
Version: 0.6.5b0
Summary: Covid-19 api wrote by python, you can get the covid-19 data from China and the world
Author: Senge-Studio
Author-email: a1356872768@gmail.com
License: GPL v3
Platform: UNKNOWN
Requires-Python: >=3.7.0
License-File: LICENSE
License-File: LICENSE-zh_CN
Requires-Dist: requests
Requires-Dist: beautifulsoup4
Requires-Dist: pypinyin
Requires-Dist: iso3166
